{
    "Ar36": {
        "error": 0.4592537694306416,
        "error_type": "SEM",
        "filter_outliers_dict": {
            "filter_outliers": false,
            "iterations": 0,
            "std_devs": 0,
            "use_iqr_filtering": false,
            "use_standard_deviation_filtering": false
        },
        "fit": "linear",
        "fn": 750,
        "include_baseline_error": false,
        "n": 750,
        "outlier_excluded": [],
        "reviewed": true,
        "user_excluded": [],
        "value": 10.651252278669748
    },
    "Ar37": {
        "error": 2.1885186328160673e-07,
        "error_type": "SEM",
        "filter_outliers_dict": {
            "filter_outliers": false,
            "iterations": 0,
            "std_devs": 0,
            "use_iqr_filtering": false,
            "use_standard_deviation_filtering": false
        },
        "fit": "linear",
        "fn": 75,
        "include_baseline_error": false,
        "n": 75,
        "outlier_excluded": [],
        "reviewed": true,
        "user_excluded": [],
        "value": -1.4686665919911907e-08
    },
    "Ar38": {
        "error": 2.3410643447203543e-07,
        "error_type": "SEM",
        "filter_outliers_dict": {
            "filter_outliers": false,
            "iterations": 0,
            "std_devs": 0,
            "use_iqr_filtering": false,
            "use_standard_deviation_filtering": false
        },
        "fit": "linear",
        "fn": 75,
        "include_baseline_error": false,
        "n": 75,
        "outlier_excluded": [],
        "reviewed": true,
        "user_excluded": [],
        "value": -2.406769745402389e-07
    },
    "Ar39": {
        "error": 1.9187423203944768e-07,
        "error_type": "SEM",
        "filter_outliers_dict": {
            "filter_outliers": false,
            "iterations": 0,
            "std_devs": 0,
            "use_iqr_filtering": false,
            "use_standard_deviation_filtering": false
        },
        "fit": "linear",
        "fn": 75,
        "include_baseline_error": false,
        "n": 75,
        "outlier_excluded": [],
        "reviewed": true,
        "user_excluded": [],
        "value": -2.892073726245081e-07
    },
    "Ar40": {
        "error": 1.8542878575924418e-06,
        "error_type": "SEM",
        "filter_outliers_dict": {
            "filter_outliers": false,
            "iterations": 0,
            "std_devs": 0,
            "use_iqr_filtering": false,
            "use_standard_deviation_filtering": false
        },
        "fit": "linear",
        "fn": 75,
        "include_baseline_error": false,
        "n": 75,
        "outlier_excluded": [],
        "reviewed": true,
        "user_excluded": [],
        "value": 5.875004450242886e-05
    }
}