{
    "Ar36": {
        "error": 7.934509742499245,
        "error_type": "SEM",
        "filter_outliers_dict": {
            "filter_outliers": false,
            "iterations": 0,
            "std_devs": 0,
            "use_iqr_filtering": false,
            "use_standard_deviation_filtering": false
        },
        "fit": "linear",
        "fn": 400,
        "include_baseline_error": false,
        "n": 400,
        "outlier_excluded": [],
        "reviewed": true,
        "user_excluded": [],
        "value": 5615.247668699853
    },
    "Ar37": {
        "error": 3.9414211057370646e-07,
        "error_type": "SEM",
        "filter_outliers_dict": {
            "filter_outliers": false,
            "iterations": 0,
            "std_devs": 0,
            "use_iqr_filtering": false,
            "use_standard_deviation_filtering": false
        },
        "fit": "linear",
        "fn": 40,
        "include_baseline_error": false,
        "n": 40,
        "outlier_excluded": [],
        "reviewed": true,
        "user_excluded": [],
        "value": 3.417622638267545e-05
    },
    "Ar38": {
        "error": 2.789044234376472e-07,
        "error_type": "SEM",
        "filter_outliers_dict": {
            "filter_outliers": false,
            "iterations": 0,
            "std_devs": 0,
            "use_iqr_filtering": false,
            "use_standard_deviation_filtering": false
        },
        "fit": "linear",
        "fn": 40,
        "include_baseline_error": false,
        "n": 40,
        "outlier_excluded": [],
        "reviewed": true,
        "user_excluded": [],
        "value": 2.0718368351326624e-05
    },
    "Ar39": {
        "error": 4.3588184978324215e-07,
        "error_type": "SEM",
        "filter_outliers_dict": {
            "filter_outliers": false,
            "iterations": 0,
            "std_devs": 0,
            "use_iqr_filtering": false,
            "use_standard_deviation_filtering": false
        },
        "fit": "linear",
        "fn": 40,
        "include_baseline_error": false,
        "n": 40,
        "outlier_excluded": [],
        "reviewed": true,
        "user_excluded": [],
        "value": 0.0001492453975965485
    },
    "Ar40": {
        "error": 2.7092110574968992e-05,
        "error_type": "SEM",
        "filter_outliers_dict": {
            "filter_outliers": false,
            "iterations": 0,
            "std_devs": 0,
            "use_iqr_filtering": false,
            "use_standard_deviation_filtering": false
        },
        "fit": "linear",
        "fn": 40,
        "include_baseline_error": false,
        "n": 40,
        "outlier_excluded": [],
        "reviewed": true,
        "user_excluded": [],
        "value": 0.03082222386431117
    }
}