{
    "AX": {
        "error": 3.021754798617286e-07,
        "error_type": "SEM",
        "filter_outliers_dict": {
            "filter_outliers": false,
            "iterations": 0,
            "std_devs": 0,
            "use_iqr_filtering": false,
            "use_standard_deviation_filtering": false
        },
        "fit": "average",
        "fn": 5,
        "include_baseline_error": false,
        "n": 5,
        "outlier_excluded": [],
        "reviewed": true,
        "user_excluded": [],
        "value": -7.533310885321498e-07
    },
    "H2": {
        "error": 4.602987142819034e-07,
        "error_type": "SEM",
        "filter_outliers_dict": {
            "filter_outliers": false,
            "iterations": 0,
            "std_devs": 0,
            "use_iqr_filtering": false,
            "use_standard_deviation_filtering": false
        },
        "fit": "average",
        "fn": 5,
        "include_baseline_error": false,
        "n": 5,
        "outlier_excluded": [],
        "reviewed": true,
        "user_excluded": [],
        "value": -5.2186852315117e-07
    },
    "H4": {
        "error": 4.104020692189571e-07,
        "error_type": "SEM",
        "filter_outliers_dict": {
            "filter_outliers": false,
            "iterations": 0,
            "std_devs": 0,
            "use_iqr_filtering": false,
            "use_standard_deviation_filtering": false
        },
        "fit": "average",
        "fn": 5,
        "include_baseline_error": false,
        "n": 5,
        "outlier_excluded": [],
        "reviewed": true,
        "user_excluded": [],
        "value": 1.5509482551578912e-07
    },
    "L2": {
        "error": 3.6785123525246403e-07,
        "error_type": "SEM",
        "filter_outliers_dict": {
            "filter_outliers": false,
            "iterations": 0,
            "std_devs": 0,
            "use_iqr_filtering": false,
            "use_standard_deviation_filtering": false
        },
        "fit": "average",
        "fn": 5,
        "include_baseline_error": false,
        "n": 5,
        "outlier_excluded": [],
        "reviewed": true,
        "user_excluded": [],
        "value": -6.884946515128831e-07
    },
    "L4": {
        "error": 0.0,
        "error_type": "SEM",
        "filter_outliers_dict": {
            "filter_outliers": false,
            "iterations": 0,
            "std_devs": 0,
            "use_iqr_filtering": false,
            "use_standard_deviation_filtering": false
        },
        "fit": "average",
        "fn": 50,
        "include_baseline_error": false,
        "n": 50,
        "outlier_excluded": [],
        "reviewed": true,
        "user_excluded": [],
        "value": 0.0
    }
}