{
    "Ar36": {
        "error": 1.6957803972253784,
        "error_type": "SEM",
        "filter_outliers_dict": {
            "filter_outliers": false,
            "iterations": 0,
            "std_devs": 0,
            "use_iqr_filtering": false,
            "use_standard_deviation_filtering": false
        },
        "fit": "linear",
        "fn": 200,
        "include_baseline_error": false,
        "n": 200,
        "outlier_excluded": [],
        "reviewed": true,
        "user_excluded": [],
        "value": 123.84969614300533
    },
    "Ar37": {
        "error": 6.714740303650681e-07,
        "error_type": "SEM",
        "filter_outliers_dict": {
            "filter_outliers": false,
            "iterations": 0,
            "std_devs": 0,
            "use_iqr_filtering": false,
            "use_standard_deviation_filtering": false
        },
        "fit": "linear",
        "fn": 20,
        "include_baseline_error": false,
        "n": 20,
        "outlier_excluded": [],
        "reviewed": true,
        "user_excluded": [],
        "value": 4.9640245811716975e-05
    },
    "Ar38": {
        "error": 5.068784215029029e-07,
        "error_type": "SEM",
        "filter_outliers_dict": {
            "filter_outliers": false,
            "iterations": 0,
            "std_devs": 0,
            "use_iqr_filtering": false,
            "use_standard_deviation_filtering": false
        },
        "fit": "linear",
        "fn": 20,
        "include_baseline_error": false,
        "n": 20,
        "outlier_excluded": [],
        "reviewed": true,
        "user_excluded": [],
        "value": 2.389806320047485e-06
    },
    "Ar39": {
        "error": 7.377027253286991e-07,
        "error_type": "SEM",
        "filter_outliers_dict": {
            "filter_outliers": false,
            "iterations": 0,
            "std_devs": 0,
            "use_iqr_filtering": false,
            "use_standard_deviation_filtering": false
        },
        "fit": "linear",
        "fn": 20,
        "include_baseline_error": false,
        "n": 20,
        "outlier_excluded": [],
        "reviewed": true,
        "user_excluded": [],
        "value": 0.00013991409816590362
    },
    "Ar40": {
        "error": 9.275093527835435e-07,
        "error_type": "SEM",
        "filter_outliers_dict": {
            "filter_outliers": false,
            "iterations": 0,
            "std_devs": 0,
            "use_iqr_filtering": false,
            "use_standard_deviation_filtering": false
        },
        "fit": "linear",
        "fn": 20,
        "include_baseline_error": false,
        "n": 20,
        "outlier_excluded": [],
        "reviewed": true,
        "user_excluded": [],
        "value": 0.0016883722434388173
    }
}