{
    "Ar36": {
        "error": 0.5438618597231986,
        "error_type": "",
        "fit": "previous",
        "references": [
            {
                "exclude": false,
                "record_id": "bu-CC-N-5767"
            }
        ],
        "value": 14.059100131547902
    },
    "Ar37": {
        "error": 2.529650275619582e-07,
        "error_type": "",
        "fit": "previous",
        "references": [
            {
                "exclude": false,
                "record_id": "bu-CC-N-5767"
            }
        ],
        "value": 4.0427613533795664e-07
    },
    "Ar38": {
        "error": 2.4863869574745884e-07,
        "error_type": "",
        "fit": "previous",
        "references": [
            {
                "exclude": false,
                "record_id": "bu-CC-N-5767"
            }
        ],
        "value": 1.4627308660113832e-06
    },
    "Ar39": {
        "error": 2.630688203777378e-07,
        "error_type": "",
        "fit": "previous",
        "references": [
            {
                "exclude": false,
                "record_id": "bu-CC-N-5767"
            }
        ],
        "value": -6.961765337864462e-07
    },
    "Ar40": {
        "error": 1.3577821341576103e-06,
        "error_type": "",
        "fit": "previous",
        "references": [
            {
                "exclude": false,
                "record_id": "bu-CC-N-5767"
            }
        ],
        "value": 6.870448282801368e-05
    }
}