{
    "AX": {
        "error": 4.0113078798025205e-07,
        "error_type": "SEM",
        "filter_outliers_dict": {
            "filter_outliers": false,
            "iterations": 0,
            "std_devs": 0,
            "use_iqr_filtering": false,
            "use_standard_deviation_filtering": false
        },
        "fit": "average",
        "fn": 5,
        "include_baseline_error": false,
        "n": 5,
        "outlier_excluded": [],
        "reviewed": true,
        "user_excluded": [],
        "value": -4.31123990551896e-07
    },
    "H2": {
        "error": 3.914040422243343e-07,
        "error_type": "SEM",
        "filter_outliers_dict": {
            "filter_outliers": false,
            "iterations": 0,
            "std_devs": 0,
            "use_iqr_filtering": false,
            "use_standard_deviation_filtering": false
        },
        "fit": "average",
        "fn": 5,
        "include_baseline_error": false,
        "n": 5,
        "outlier_excluded": [],
        "reviewed": true,
        "user_excluded": [],
        "value": -2.5696078864712036e-08
    },
    "H4": {
        "error": 3.9545932515935496e-07,
        "error_type": "SEM",
        "filter_outliers_dict": {
            "filter_outliers": false,
            "iterations": 0,
            "std_devs": 0,
            "use_iqr_filtering": false,
            "use_standard_deviation_filtering": false
        },
        "fit": "average",
        "fn": 5,
        "include_baseline_error": false,
        "n": 5,
        "outlier_excluded": [],
        "reviewed": true,
        "user_excluded": [],
        "value": -4.581663887393006e-07
    },
    "L2": {
        "error": 3.966548987460327e-07,
        "error_type": "SEM",
        "filter_outliers_dict": {
            "filter_outliers": false,
            "iterations": 0,
            "std_devs": 0,
            "use_iqr_filtering": false,
            "use_standard_deviation_filtering": false
        },
        "fit": "average",
        "fn": 5,
        "include_baseline_error": false,
        "n": 5,
        "outlier_excluded": [],
        "reviewed": true,
        "user_excluded": [],
        "value": -1.340212332934243e-06
    },
    "L4": {
        "error": 0.002000000029802322,
        "error_type": "SEM",
        "filter_outliers_dict": {
            "filter_outliers": false,
            "iterations": 0,
            "std_devs": 0,
            "use_iqr_filtering": false,
            "use_standard_deviation_filtering": false
        },
        "fit": "average",
        "fn": 50,
        "include_baseline_error": false,
        "n": 50,
        "outlier_excluded": [],
        "reviewed": true,
        "user_excluded": [],
        "value": 0.0020000000298023225
    }
}