{
    "Ar36": {
        "error": 1.2021333433991526,
        "error_type": "SEM",
        "filter_outliers_dict": {
            "filter_outliers": false,
            "iterations": 0,
            "std_devs": 0,
            "use_iqr_filtering": false,
            "use_standard_deviation_filtering": false
        },
        "fit": "linear",
        "fn": 200,
        "include_baseline_error": false,
        "n": 200,
        "outlier_excluded": [],
        "reviewed": true,
        "user_excluded": [],
        "value": 42.24671055885757
    },
    "Ar37": {
        "error": 2.702229749649675e-07,
        "error_type": "SEM",
        "filter_outliers_dict": {
            "filter_outliers": false,
            "iterations": 0,
            "std_devs": 0,
            "use_iqr_filtering": false,
            "use_standard_deviation_filtering": false
        },
        "fit": "linear",
        "fn": 20,
        "include_baseline_error": false,
        "n": 20,
        "outlier_excluded": [],
        "reviewed": true,
        "user_excluded": [],
        "value": 1.5438366162966582e-06
    },
    "Ar38": {
        "error": 4.0416257591322546e-07,
        "error_type": "SEM",
        "filter_outliers_dict": {
            "filter_outliers": false,
            "iterations": 0,
            "std_devs": 0,
            "use_iqr_filtering": false,
            "use_standard_deviation_filtering": false
        },
        "fit": "linear",
        "fn": 20,
        "include_baseline_error": false,
        "n": 20,
        "outlier_excluded": [],
        "reviewed": true,
        "user_excluded": [],
        "value": 1.9309029667730764e-05
    },
    "Ar39": {
        "error": 1.5320057598294485e-06,
        "error_type": "SEM",
        "filter_outliers_dict": {
            "filter_outliers": false,
            "iterations": 0,
            "std_devs": 0,
            "use_iqr_filtering": false,
            "use_standard_deviation_filtering": false
        },
        "fit": "linear",
        "fn": 20,
        "include_baseline_error": false,
        "n": 20,
        "outlier_excluded": [],
        "reviewed": true,
        "user_excluded": [],
        "value": 0.0015478657497196415
    },
    "Ar40": {
        "error": 3.955994635381502e-06,
        "error_type": "SEM",
        "filter_outliers_dict": {
            "filter_outliers": false,
            "iterations": 0,
            "std_devs": 0,
            "use_iqr_filtering": false,
            "use_standard_deviation_filtering": false
        },
        "fit": "linear",
        "fn": 20,
        "include_baseline_error": false,
        "n": 20,
        "outlier_excluded": [],
        "reviewed": true,
        "user_excluded": [],
        "value": 0.008520071048932168
    }
}